folder2dataset_dicom.py
folder2dataset_dicom-0.1.dist-info/METADATA
folder2dataset_dicom-0.1.dist-info/WHEEL
folder2dataset_dicom-0.1.dist-info/top_level.txt
folder2dataset_dicom-0.1.dist-info/RECORD
