Metadata-Version: 2.1
Name: folder2dataset-dicom
Version: 0.1
Summary: Create Pytorch Dataset from a folder with dicom images
Home-page: UNKNOWN
Author: Thedoropoulos Dimitrios
Author-email: dimitheodoro@gmail.com
License: UNKNOWN
Platform: UNKNOWN
